taxonomy/__init__.py
taxonomy/admin.py
taxonomy/apps.py
taxonomy/choices.py
taxonomy/constants.py
taxonomy/enums.py
taxonomy/exceptions.py
taxonomy/forms.py
taxonomy/migrations_utils.py
taxonomy/models.py
taxonomy/serializers.py
taxonomy/tasks.py
taxonomy/urls.py
taxonomy/utils.py
taxonomy/views.py
taxonomy/algolia/__init__.py
taxonomy/algolia/client.py
taxonomy/algolia/constants.py
taxonomy/algolia/serializers.py
taxonomy/algolia/utils.py
taxonomy/api/filters.py
taxonomy/api/permissions.py
taxonomy/api/urls.py
taxonomy/api/v1/serializers.py
taxonomy/api/v1/urls.py
taxonomy/api/v1/views.py
taxonomy/emsi/__init__.py
taxonomy/emsi/client.py
taxonomy/emsi/parsers/__init__.py
taxonomy/emsi/parsers/skill_parsers.py
taxonomy/management/__init__.py
taxonomy/management/commands/__init__.py
taxonomy/management/commands/fetch_skill_details.py
taxonomy/management/commands/finalize_xblockskill_tags.py
taxonomy/management/commands/generate_job_descriptions.py
taxonomy/management/commands/populate_job_names.py
taxonomy/management/commands/refresh_course_skills.py
taxonomy/management/commands/refresh_job_postings_data.py
taxonomy/management/commands/refresh_job_skills.py
taxonomy/management/commands/refresh_program_skills.py
taxonomy/management/commands/refresh_xblock_skills.py
taxonomy/management/commands/reindex_algolia.py
taxonomy/migrations/0001_initial.py
taxonomy/migrations/0002_job_jobskills.py
taxonomy/migrations/0003_auto_20200916_1019.py
taxonomy/migrations/0004_auto_20210113_0452.py
taxonomy/migrations/0005_blacklistedcourseskill.py
taxonomy/migrations/0006_auto_20210128_0135.py
taxonomy/migrations/0007_delete_all_records.py
taxonomy/migrations/0008_auto_20210216_0710.py
taxonomy/migrations/0009_skill_description.py
taxonomy/migrations/0010_auto_20210409_0256.py
taxonomy/migrations/0011_auto_20210412_0241.py
taxonomy/migrations/0012_auto_20210412_0424.py
taxonomy/migrations/0013_remove_courseskills_course_id.py
taxonomy/migrations/0014_auto_20210416_0548.py
taxonomy_connector-2.3.16.dist-info/licenses/LICENSE
taxonomy_connector-2.3.16.dist-info/METADATA
taxonomy_connector-2.3.16.dist-info/WHEEL
taxonomy_connector-2.3.16.dist-info/top_level.txt
taxonomy_connector-2.3.16.dist-info/RECORD
