Metadata-Version: 2.4
Name: taxonomy-connector
Version: 2.3.16
Summary: Taxonomy connector
Home-page: https://github.com/openedx/taxonomy-connector
Author: edX
Author-email: oscm@edx.org
License: MIT
Classifier: Framework :: Django
Classifier: Framework :: Django :: 4.2
Classifier: Framework :: Django :: 5.2
Classifier: Programming Language :: Python :: 3
Classifier: Programming Language :: Python :: 3.12
License-File: LICENSE
Requires-Dist: Django
Requires-Dist: djangorestframework
Requires-Dist: django-model-utils
Requires-Dist: django-solo
Requires-Dist: pytz
Requires-Dist: edx-rest-api-client
Requires-Dist: edx-django-utils
Requires-Dist: edx-opaque-keys
Requires-Dist: celery
Requires-Dist: algoliasearch
Requires-Dist: django-ses
Requires-Dist: beautifulsoup4
Requires-Dist: django-choices
Requires-Dist: django-filter
Requires-Dist: openedx-events
Requires-Dist: django-object-actions
Dynamic: author
Dynamic: author-email
Dynamic: classifier
Dynamic: description
Dynamic: home-page
Dynamic: license
Dynamic: license-file
Dynamic: requires-dist
Dynamic: summary
